xontrib/chatgpt.py
xontrib_chatgpt/__init__.py
xontrib_chatgpt/args.py
xontrib_chatgpt/chatgpt.py
xontrib_chatgpt/chatmanager.py
xontrib_chatgpt/completers.py
xontrib_chatgpt/events.py
xontrib_chatgpt/exceptions.py
xontrib_chatgpt/lazyobjs.py
xontrib_chatgpt/utils.py
xontrib_chatgpt_v1-1.0.0.dist-info/LICENSE
xontrib_chatgpt_v1-1.0.0.dist-info/METADATA
xontrib_chatgpt_v1-1.0.0.dist-info/WHEEL
xontrib_chatgpt_v1-1.0.0.dist-info/top_level.txt
xontrib_chatgpt_v1-1.0.0.dist-info/RECORD
